jutils/__init__.py
jutils/cli.py
psutilsj-1.2.dist-info/METADATA
psutilsj-1.2.dist-info/WHEEL
psutilsj-1.2.dist-info/entry_points.txt
psutilsj-1.2.dist-info/top_level.txt
psutilsj-1.2.dist-info/RECORD
