Metadata-Version: 2.4
Name: psutilsj
Version: 1.2
Summary: CLI tool to SSH and run j.py
Author: ubuntu
Requires-Python: >=3.6
Dynamic: author
Dynamic: requires-python
Dynamic: summary
